ziffy/__init__.py
ziffy/__main__.py
ziffy/cli/__init__.py
ziffy/cli/datasets.py
ziffy/datasets.py
ziffy/db/__init__.py
ziffy/db/datasets.py
ziffy/db.py
ziffy/oldmain.py
ziffy/regex.py
ziffy/tree.py
ziffy/utils.py
ziffy-0.1.0.dist-info/METADATA
ziffy-0.1.0.dist-info/WHEEL
ziffy-0.1.0.dist-info/RECORD
